{
  "version": "7",
  "dialect": "postgresql",
  "entries": [
    {
      "idx": 0,
      "version": "7",
      "when": 1780148766287,
      "tag": "0000_mushy_stephen_strange",
      "breakpoints": true
    },
    {
      "idx": 1,
      "version": "7",
      "when": 1780151864089,
      "tag": "0001_mushy_wiccan",
      "breakpoints": true
    },
    {
      "idx": 2,
      "version": "7",
      "when": 1780328489893,
      "tag": "0002_yellow_longshot",
      "breakpoints": true
    },
    {
      "idx": 3,
      "version": "7",
      "when": 1780490920831,
      "tag": "0003_rainy_zaran",
      "breakpoints": true
    },
    {
      "idx": 4,
      "version": "7",
      "when": 1781244559218,
      "tag": "0004_shallow_talon",
      "breakpoints": true
    },
    {
      "idx": 5,
      "version": "7",
      "when": 1783229632680,
      "tag": "0005_tidy_logan",
      "breakpoints": true
    },
    {
      "idx": 6,
      "version": "7",
      "when": 1783835510985,
      "tag": "0006_smooth_power_man",
      "breakpoints": true
    },
    {
      "idx": 7,
      "version": "7",
      "when": 1783838698192,
      "tag": "0007_huge_malice",
      "breakpoints": true
    },
    {
      "idx": 8,
      "version": "7",
      "when": 1784264268001,
      "tag": "0008_amusing_gwen_stacy",
      "breakpoints": true
    },
    {
      "idx": 9,
      "version": "7",
      "when": 1784712730335,
      "tag": "0009_boring_layla_miller",
      "breakpoints": true
    }
  ]
}